aglvq/__init__.py
aglvq/confusion_matrix.py
aglvq/constraints.py
aglvq/dataset.py
aglvq/distance.py
aglvq/importances.py
aglvq/initializer.py
aglvq/input_layer.py
aglvq/layers.py
aglvq/losses.py
aglvq/model.py
aglvq/plotting.py
aglvq/proto.py
aglvq-1.0.dist-info/LICENSE.md
aglvq-1.0.dist-info/METADATA
aglvq-1.0.dist-info/WHEEL
aglvq-1.0.dist-info/top_level.txt
aglvq-1.0.dist-info/RECORD
